{
    "ScoreTitle": "Star Quality for all known players, between 2019-07-01 and 2019-08-01",
    "ScoreGreaterOrEqualDate": "2019-08-01",
    "ScoreLessDate": "2019-07-01",
    "Player": [
        {},
        {
            "Name": "Little Tank",
            "StarQualityPerGame": 54.91,
            "TotalStarQuality": 274.57,
            "AverageOpponents": 12.4,
            "gamesPlayed": 5,
            "AverageRank": 2.8,
            "ChangeInRank": "\u21930.94",
            "ChangeInPlayers": "\u21914.26",
            "ChangeInSQPerGame": "\u219119.21"
        },
        {
            "Name": "Entity",
            "StarQualityPerGame": 33.6,
            "TotalStarQuality": 235.2,
            "AverageOpponents": 12.0,
            "gamesPlayed": 7,
            "AverageRank": 4.29,
            "ChangeInRank": "\u21930.54",
            "ChangeInPlayers": "\u21915.08",
            "ChangeInSQPerGame": "\u219120.84"
        },
        {
            "Name": "Hero of Light",
            "StarQualityPerGame": 24.03,
            "TotalStarQuality": 168.23,
            "AverageOpponents": 11.57,
            "gamesPlayed": 7,
            "AverageRank": 5.57,
            "ChangeInRank": "\u21931.5",
            "ChangeInPlayers": "\u21914.57",
            "ChangeInSQPerGame": "\u219111.98"
        },
        {
            "Name": "Archer",
            "StarQualityPerGame": 23.66,
            "TotalStarQuality": 473.2,
            "AverageOpponents": 9.1,
            "gamesPlayed": 20,
            "AverageRank": 3.5,
            "ChangeInRank": "\u21930.79",
            "ChangeInPlayers": "\u21911.6",
            "ChangeInSQPerGame": "\u21912.94"
        },
        {
            "Name": "[Insomniac]",
            "StarQualityPerGame": 22.34,
            "TotalStarQuality": 201.1,
            "AverageOpponents": 12.0,
            "gamesPlayed": 9,
            "AverageRank": 6.44,
            "ChangeInRank": "\u21933.63",
            "ChangeInPlayers": "\u21914.91",
            "ChangeInSQPerGame": "\u21914.5"
        },
        {
            "Name": "Morrigan",
            "StarQualityPerGame": 20.17,
            "TotalStarQuality": 121.0,
            "AverageOpponents": 11.0,
            "gamesPlayed": 6,
            "AverageRank": 6.0,
            "ChangeInRank": "\u21930.13",
            "ChangeInPlayers": "\u21913.38",
            "ChangeInSQPerGame": "\u219110.27"
        },
        {
            "Name": "Unagi",
            "StarQualityPerGame": 19.6,
            "TotalStarQuality": 490.0,
            "AverageOpponents": 8.4,
            "gamesPlayed": 25,
            "AverageRank": 3.6,
            "ChangeInRank": "\u21910.4",
            "ChangeInPlayers": "\u21930.8",
            "ChangeInSQPerGame": "\u21931.56"
        },
        {
            "Name": "Azrael",
            "StarQualityPerGame": 19.11,
            "TotalStarQuality": 95.56,
            "AverageOpponents": 11.4,
            "gamesPlayed": 5,
            "AverageRank": 6.8,
            "ChangeInRank": "\u21933.64",
            "ChangeInPlayers": "\u21915.36",
            "ChangeInSQPerGame": "\u21917.57"
        },
        {
            "Name": "S O S",
            "StarQualityPerGame": 18.77,
            "TotalStarQuality": 150.13,
            "AverageOpponents": 10.5,
            "gamesPlayed": 8,
            "AverageRank": 5.88,
            "ChangeInRank": "\u21931.72",
            "ChangeInPlayers": "\u21913.55",
            "ChangeInSQPerGame": "\u21917.13"
        },
        {
            "Name": "Calpinator",
            "StarQualityPerGame": 18.11,
            "TotalStarQuality": 126.75,
            "AverageOpponents": 12.14,
            "gamesPlayed": 7,
            "AverageRank": 8.14,
            "ChangeInRank": "\u21934.14",
            "ChangeInPlayers": "\u21914.98",
            "ChangeInSQPerGame": "\u21915.27"
        },
        {
            "Name": "Fur Ball",
            "StarQualityPerGame": 16.96,
            "TotalStarQuality": 135.69,
            "AverageOpponents": 10.5,
            "gamesPlayed": 8,
            "AverageRank": 6.5,
            "ChangeInRank": null,
            "ChangeInPlayers": null,
            "ChangeInSQPerGame": null
        },
        {
            "Name": "HiJack",
            "StarQualityPerGame": 16.78,
            "TotalStarQuality": 452.97,
            "AverageOpponents": 8.0,
            "gamesPlayed": 27,
            "AverageRank": 3.81,
            "ChangeInRank": "\u21911.85",
            "ChangeInPlayers": "\u21931.0",
            "ChangeInSQPerGame": "\u21912.48"
        },
        {
            "Name": "Sn3aky",
            "StarQualityPerGame": 16.35,
            "TotalStarQuality": 196.2,
            "AverageOpponents": 7.92,
            "gamesPlayed": 12,
            "AverageRank": 3.83,
            "ChangeInRank": "\u21930.5",
            "ChangeInPlayers": "\u21910.25",
            "ChangeInSQPerGame": "\u21931.28"
        },
        {
            "Name": "Natsudragneel",
            "StarQualityPerGame": 16.3,
            "TotalStarQuality": 195.56,
            "AverageOpponents": 9.75,
            "gamesPlayed": 12,
            "AverageRank": 5.83,
            "ChangeInRank": "\u21930.44",
            "ChangeInPlayers": "\u21912.81",
            "ChangeInSQPerGame": "\u21917.35"
        },
        {
            "Name": "Assassin",
            "StarQualityPerGame": 14.77,
            "TotalStarQuality": 88.62,
            "AverageOpponents": 8.0,
            "gamesPlayed": 6,
            "AverageRank": 4.33,
            "ChangeInRank": "\u21930.57",
            "ChangeInPlayers": "\u21911.81",
            "ChangeInSQPerGame": "\u21914.58"
        },
        {
            "Name": "Killa",
            "StarQualityPerGame": 14.29,
            "TotalStarQuality": 128.57,
            "AverageOpponents": 10.0,
            "gamesPlayed": 9,
            "AverageRank": 7.0,
            "ChangeInRank": "\u21933.5",
            "ChangeInPlayers": "\u21911.67",
            "ChangeInSQPerGame": "\u21935.56"
        },
        {
            "Name": "Phoenix Warrior",
            "StarQualityPerGame": 13.78,
            "TotalStarQuality": 110.25,
            "AverageOpponents": 10.5,
            "gamesPlayed": 8,
            "AverageRank": 8.0,
            "ChangeInRank": null,
            "ChangeInPlayers": null,
            "ChangeInSQPerGame": null
        },
        {
            "Name": "<!-- Blaze -->",
            "StarQualityPerGame": 13.25,
            "TotalStarQuality": 331.19,
            "AverageOpponents": 7.6,
            "gamesPlayed": 25,
            "AverageRank": 4.36,
            "ChangeInRank": "\u21910.57",
            "ChangeInPlayers": "\u21930.33",
            "ChangeInSQPerGame": "\u21910.49"
        },
        {
            "Name": "Winter",
            "StarQualityPerGame": 12.58,
            "TotalStarQuality": 264.09,
            "AverageOpponents": 8.86,
            "gamesPlayed": 21,
            "AverageRank": 6.24,
            "ChangeInRank": "\u21930.68",
            "ChangeInPlayers": "\u21911.3",
            "ChangeInSQPerGame": "\u21912.3"
        },
        {
            "Name": "Hana",
            "StarQualityPerGame": 9.02,
            "TotalStarQuality": 144.33,
            "AverageOpponents": 7.88,
            "gamesPlayed": 16,
            "AverageRank": 6.88,
            "ChangeInRank": null,
            "ChangeInPlayers": null,
            "ChangeInSQPerGame": null
        },
        {
            "Name": "(Apollo)",
            "StarQualityPerGame": 3.57,
            "TotalStarQuality": 42.88,
            "AverageOpponents": 2.25,
            "gamesPlayed": 12,
            "AverageRank": 1.42,
            "ChangeInRank": "\u21910.21",
            "ChangeInPlayers": "\u21910.25",
            "ChangeInSQPerGame": "\u21911.11"
        },
        {
            "Name": "Destroyer",
            "StarQualityPerGame": 3.2,
            "TotalStarQuality": 25.6,
            "AverageOpponents": 2.0,
            "gamesPlayed": 8,
            "AverageRank": 1.25,
            "ChangeInRank": null,
            "ChangeInPlayers": null,
            "ChangeInSQPerGame": null
        },
        {
            "Name": "UltimateWarrior",
            "StarQualityPerGame": 3.2,
            "TotalStarQuality": 12.8,
            "AverageOpponents": 2.0,
            "gamesPlayed": 4,
            "AverageRank": 1.25,
            "ChangeInRank": null,
            "ChangeInPlayers": null,
            "ChangeInSQPerGame": null
        },
        {
            "Name": "Mr ChatterBob",
            "StarQualityPerGame": 2.61,
            "TotalStarQuality": 41.78,
            "AverageOpponents": 1.94,
            "gamesPlayed": 16,
            "AverageRank": 1.44,
            "ChangeInRank": "\u21930.06",
            "ChangeInPlayers": "\u21930.06",
            "ChangeInSQPerGame": "\u21930.3"
        },
        {
            "Name": "Ninjashyper",
            "StarQualityPerGame": 2.5,
            "TotalStarQuality": 10.0,
            "AverageOpponents": 2.5,
            "gamesPlayed": 4,
            "AverageRank": 2.5,
            "ChangeInRank": null,
            "ChangeInPlayers": null,
            "ChangeInSQPerGame": null
        },
        {
            "Name": "Insanity",
            "StarQualityPerGame": 2.29,
            "TotalStarQuality": 9.14,
            "AverageOpponents": 2.0,
            "gamesPlayed": 4,
            "AverageRank": 1.75,
            "ChangeInRank": null,
            "ChangeInPlayers": null,
            "ChangeInSQPerGame": null
        },
        {
            "Name": "HastlavistaBaby",
            "StarQualityPerGame": 2.29,
            "TotalStarQuality": 18.29,
            "AverageOpponents": 2.0,
            "gamesPlayed": 8,
            "AverageRank": 1.75,
            "ChangeInRank": null,
            "ChangeInPlayers": null,
            "ChangeInSQPerGame": null
        },
        {
            "Name": "Commandoz",
            "StarQualityPerGame": 1.0,
            "TotalStarQuality": 3.0,
            "AverageOpponents": 1.0,
            "gamesPlayed": 3,
            "AverageRank": 1.0,
            "ChangeInRank": null,
            "ChangeInPlayers": null,
            "ChangeInSQPerGame": null
        },
        {
            "Name": "Section",
            "StarQualityPerGame": 1.0,
            "TotalStarQuality": 4.0,
            "AverageOpponents": 1.0,
            "gamesPlayed": 4,
            "AverageRank": 1.0,
            "ChangeInRank": null,
            "ChangeInPlayers": null,
            "ChangeInSQPerGame": null
        }
    ]
}