{
    "ScoreTitle": "Average Scores for known players, in Standard Games, between 2020-09-01 and 2020-08-01",
    "ScoreGreaterOrEqualDate": "2020-08-01",
    "ScoreLessDate": "2020-09-01",
    "Player": [
        {},
        {
            "Name": "Jububley",
            "AverageScore": 11013,
            "MissionsPlayed": 3,
            "ChangeInScore": null
        },
        {
            "Name": "Laser",
            "AverageScore": 9831,
            "MissionsPlayed": 3,
            "ChangeInScore": null
        },
        {
            "Name": "Bomber Beccs ",
            "AverageScore": 8826,
            "MissionsPlayed": 1,
            "ChangeInScore": null
        },
        {
            "Name": "Haribo",
            "AverageScore": 8219,
            "MissionsPlayed": 3,
            "ChangeInScore": null
        },
        {
            "Name": "Partyfire",
            "AverageScore": 8035,
            "MissionsPlayed": 2,
            "ChangeInScore": null
        },
        {
            "Name": "Blaster",
            "AverageScore": 7639,
            "MissionsPlayed": 3,
            "ChangeInScore": null
        },
        {
            "Name": "Mikey Magnum",
            "AverageScore": 7379,
            "MissionsPlayed": 3,
            "ChangeInScore": null
        },
        {
            "Name": "Spiderman Sam",
            "AverageScore": 5732,
            "MissionsPlayed": 2,
            "ChangeInScore": null
        },
        {
            "Name": "Noah Destroyer",
            "AverageScore": 5725,
            "MissionsPlayed": 2,
            "ChangeInScore": null
        },
        {
            "Name": "LaserGunner 815",
            "AverageScore": 5500,
            "MissionsPlayed": 2,
            "ChangeInScore": null
        },
        {
            "Name": "Immortal-Guy",
            "AverageScore": 4441,
            "MissionsPlayed": 1,
            "ChangeInScore": null
        }
    ]
}