{
    "GoldenPlayer": {
        "PlayerName": "-=Valroc=-",
        "HomeArenaTrunc": "LaserZone, Bradford, UK",
        "SkillLevelName": "Lasermaster",
        "MonthlyGamesPlayed": 20,
        "AllGamesPlayed": 1690,
        "StarQuality": "44.02",
        "Achievements": 103,
        "GGName": "Infection",
        "GGRank": "1st",
        "GGStars": "121 stars",
        "GGVanq1": "Noob!",
        "GGVanq2": "Psycho",
        "GGVanq3": "Hero of Light",
        "GGVanq4": "7 others",
        "GAName": "General",
        "GADesc": "Win 25 games of SM5.",
        "GAOthers": "No one else has"
    },
    "SilverPlayer": {
        "PlayerName": "Agent Jaikei",
        "HomeArenaTrunc": "LaserZone, Huddersfield, UK",
        "SkillLevelName": "Lasermaster",
        "MonthlyGamesPlayed": 5,
        "AllGamesPlayed": 454,
        "StarQuality": "24.77",
        "Achievements": 88,
        "GGName": "Shadows - Solo",
        "GGRank": "1st",
        "GGStars": "100 stars",
        "GGVanq1": "Road1to1Toast",
        "GGVanq2": "Hero of Light",
        "GGVanq3": "Noob!",
        "GGVanq4": "6 others",
        "GAName": "Survivalist",
        "GADesc": "End the game with at least 15 lives as Medic in SM5.",
        "GAOthers": "5 others have"
    },
    "BronzePlayer": {
        "PlayerName": "Hero of Light",
        "HomeArenaTrunc": "LaserZone, Huddersfield, UK",
        "SkillLevelName": "Starlord",
        "MonthlyGamesPlayed": 10,
        "AllGamesPlayed": 244,
        "StarQuality": "24.65",
        "Achievements": 62,
        "GGName": "Borg",
        "GGRank": "1st",
        "GGStars": "36 stars",
        "GGVanq1": "Road1to1Toast",
        "GGVanq2": "Dad1of1Toast",
        "GGVanq3": "Blaze",
        "GGVanq4": "2 others",
        "GAName": "Leap To It",
        "GADesc": "Play a game on February 29th.",
        "GAOthers": "No one else has"
    },
    "OtherPlayer1": {
        "PlayerName": "Ninja_Cole",
        "HomeArenaTrunc": "LaserZone, Huddersfield, UK",
        "SkillLevelName": "Starlord",
        "MonthlyGamesPlayed": 2,
        "AllGamesPlayed": 29,
        "StarQuality": "1.00",
        "Achievements": 41,
        "GAName": "Back To Back",
        "GADesc": "Play 2 months in a row.",
        "GAOthers": "50 others have"
    },
    "OtherPlayer2": {
        "PlayerName": "Sn3aky",
        "HomeArenaTrunc": "LaserZone, Huddersfield, UK",
        "SkillLevelName": "Starlord",
        "MonthlyGamesPlayed": 0,
        "AllGamesPlayed": 1624,
        "StarQuality": "0.00",
        "Achievements": 96,
        "GAName": "Maximus",
        "GADesc": "Survive and win a game of Gladiator as a Level 6 Lasermaster. (Minimum 10 players)",
        "GAOthers": "6 others have"
    },
    "SiteNameShort": "LaserZone Huddersfield"
}