{
    "brightestStars": [
        {
            "gamertag": "Goku",
            "averageStars": "30.47",
            "averageOpponents": "8.73",
            "averageRank": "3.82",
            "gamesPlayed": "11"
        },
        {
            "gamertag": "Rayth",
            "averageStars": "24.95",
            "averageOpponents": "5.97",
            "averageRank": "2.05",
            "gamesPlayed": "39"
        },
        {
            "gamertag": "Winter",
            "averageStars": "20.42",
            "averageOpponents": "7.86",
            "averageRank": "5.71",
            "gamesPlayed": "7"
        },
        {
            "gamertag": "C'tri",
            "averageStars": "19.69",
            "averageOpponents": "4.40",
            "averageRank": "1.45",
            "gamesPlayed": "62"
        },
        {
            "gamertag": "Macintyre",
            "averageStars": "18.75",
            "averageOpponents": "5.00",
            "averageRank": "1.50",
            "gamesPlayed": "2"
        },
        {
            "gamertag": "T D",
            "averageStars": "18.41",
            "averageOpponents": "8.38",
            "averageRank": "5.00",
            "gamesPlayed": "13"
        },
        {
            "gamertag": "Achilles",
            "averageStars": "18.29",
            "averageOpponents": "4.77",
            "averageRank": "2.15",
            "gamesPlayed": "48"
        },
        {
            "gamertag": "Damo",
            "averageStars": "16.18",
            "averageOpponents": "11.40",
            "averageRank": "9.00",
            "gamesPlayed": "5"
        },
        {
            "gamertag": "Minnie",
            "averageStars": "16.17",
            "averageOpponents": "8.70",
            "averageRank": "5.40",
            "gamesPlayed": "10"
        },
        {
            "gamertag": "Reboot",
            "averageStars": "15.66",
            "averageOpponents": "6.24",
            "averageRank": "3.48",
            "gamesPlayed": "25"
        },
        {
            "gamertag": "Omega",
            "averageStars": "15.62",
            "averageOpponents": "8.00",
            "averageRank": "5.25",
            "gamesPlayed": "4"
        },
        {
            "gamertag": "Robo_h34d",
            "averageStars": "15.52",
            "averageOpponents": "7.65",
            "averageRank": "4.57",
            "gamesPlayed": "23"
        },
        {
            "gamertag": "Korg",
            "averageStars": "15.00",
            "averageOpponents": "12.00",
            "averageRank": "10.00",
            "gamesPlayed": "4"
        },
        {
            "gamertag": "JammyDodger",
            "averageStars": "14.04",
            "averageOpponents": "5.18",
            "averageRank": "2.27",
            "gamesPlayed": "11"
        },
        {
            "gamertag": "Soul",
            "averageStars": "12.63",
            "averageOpponents": "9.00",
            "averageRank": "6.67",
            "gamesPlayed": "3"
        },
        {
            "gamertag": "Mike Hunt",
            "averageStars": "11.51",
            "averageOpponents": "5.71",
            "averageRank": "3.54",
            "gamesPlayed": "24"
        },
        {
            "gamertag": "ThatGuysFriend",
            "averageStars": "11.22",
            "averageOpponents": "5.25",
            "averageRank": "2.63",
            "gamesPlayed": "8"
        },
        {
            "gamertag": "Captain Kitty",
            "averageStars": "11.21",
            "averageOpponents": "4.33",
            "averageRank": "2.33",
            "gamesPlayed": "6"
        },
        {
            "gamertag": "SpeedyDylan",
            "averageStars": "11.20",
            "averageOpponents": "8.00",
            "averageRank": "6.25",
            "gamesPlayed": "4"
        },
        {
            "gamertag": "<*(((<",
            "averageStars": "11.14",
            "averageOpponents": "4.33",
            "averageRank": "2.50",
            "gamesPlayed": "6"
        },
        {
            "gamertag": "Mindi",
            "averageStars": "11.03",
            "averageOpponents": "6.85",
            "averageRank": "4.92",
            "gamesPlayed": "13"
        },
        {
            "gamertag": "Oscar",
            "averageStars": "10.86",
            "averageOpponents": "4.27",
            "averageRank": "1.87",
            "gamesPlayed": "15"
        },
        {
            "gamertag": "Jj",
            "averageStars": "10.33",
            "averageOpponents": "4.39",
            "averageRank": "2.48",
            "gamesPlayed": "31"
        },
        {
            "gamertag": "Ghost 57",
            "averageStars": "10.00",
            "averageOpponents": "3.00",
            "averageRank": "1.00",
            "gamesPlayed": "4"
        },
        {
            "gamertag": "Bfl2",
            "averageStars": "9.67",
            "averageOpponents": "3.67",
            "averageRank": "1.50",
            "gamesPlayed": "6"
        },
        {
            "gamertag": "Star Destroyer",
            "averageStars": "9.67",
            "averageOpponents": "3.00",
            "averageRank": "1.00",
            "gamesPlayed": "3"
        },
        {
            "gamertag": "Lewis",
            "averageStars": "9.33",
            "averageOpponents": "4.00",
            "averageRank": "2.33",
            "gamesPlayed": "3"
        },
        {
            "gamertag": "Aidan",
            "averageStars": "8.88",
            "averageOpponents": "3.50",
            "averageRank": "1.75",
            "gamesPlayed": "4"
        },
        {
            "gamertag": "Midge",
            "averageStars": "8.44",
            "averageOpponents": "4.00",
            "averageRank": "2.67",
            "gamesPlayed": "3"
        },
        {
            "gamertag": "Overdrive",
            "averageStars": "8.42",
            "averageOpponents": "3.23",
            "averageRank": "1.62",
            "gamesPlayed": "13"
        },
        {
            "gamertag": "Johnny",
            "averageStars": "8.33",
            "averageOpponents": "2.67",
            "averageRank": "1.00",
            "gamesPlayed": "6"
        },
        {
            "gamertag": "Shade",
            "averageStars": "7.97",
            "averageOpponents": "6.06",
            "averageRank": "5.00",
            "gamesPlayed": "16"
        },
        {
            "gamertag": "Billybob",
            "averageStars": "7.70",
            "averageOpponents": "6.60",
            "averageRank": "5.75",
            "gamesPlayed": "20"
        },
        {
            "gamertag": "Alpha",
            "averageStars": "7.65",
            "averageOpponents": "6.33",
            "averageRank": "5.50",
            "gamesPlayed": "12"
        },
        {
            "gamertag": "PlagueDoctor",
            "averageStars": "7.52",
            "averageOpponents": "5.14",
            "averageRank": "3.57",
            "gamesPlayed": "7"
        },
        {
            "gamertag": "Angel of Death",
            "averageStars": "7.47",
            "averageOpponents": "2.87",
            "averageRank": "1.27",
            "gamesPlayed": "15"
        },
        {
            "gamertag": "Andrew",
            "averageStars": "7.42",
            "averageOpponents": "3.50",
            "averageRank": "2.13",
            "gamesPlayed": "8"
        },
        {
            "gamertag": "DragonNinjaIsla",
            "averageStars": "7.29",
            "averageOpponents": "2.86",
            "averageRank": "1.57",
            "gamesPlayed": "7"
        },
        {
            "gamertag": "Mcbeardy",
            "averageStars": "7.11",
            "averageOpponents": "4.33",
            "averageRank": "2.83",
            "gamesPlayed": "6"
        },
        {
            "gamertag": "Face",
            "averageStars": "7.00",
            "averageOpponents": "3.00",
            "averageRank": "1.50",
            "gamesPlayed": "6"
        },
        {
            "gamertag": "Bfl1",
            "averageStars": "6.83",
            "averageOpponents": "3.67",
            "averageRank": "2.50",
            "gamesPlayed": "6"
        },
        {
            "gamertag": "Fancy Pants",
            "averageStars": "6.77",
            "averageOpponents": "5.00",
            "averageRank": "4.14",
            "gamesPlayed": "7"
        },
        {
            "gamertag": "Stephen",
            "averageStars": "6.75",
            "averageOpponents": "3.50",
            "averageRank": "2.13",
            "gamesPlayed": "8"
        },
        {
            "gamertag": "Outlander",
            "averageStars": "6.67",
            "averageOpponents": "3.22",
            "averageRank": "2.00",
            "gamesPlayed": "9"
        },
        {
            "gamertag": "404 Unf",
            "averageStars": "6.47",
            "averageOpponents": "3.00",
            "averageRank": "1.67",
            "gamesPlayed": "15"
        },
        {
            "gamertag": "Tonymcl1002",
            "averageStars": "6.39",
            "averageOpponents": "3.33",
            "averageRank": "2.00",
            "gamesPlayed": "6"
        },
        {
            "gamertag": "Smokey Bandit",
            "averageStars": "6.38",
            "averageOpponents": "5.25",
            "averageRank": "4.50",
            "gamesPlayed": "4"
        },
        {
            "gamertag": "James",
            "averageStars": "6.25",
            "averageOpponents": "3.50",
            "averageRank": "2.63",
            "gamesPlayed": "8"
        },
        {
            "gamertag": "P-Diddy",
            "averageStars": "6.22",
            "averageOpponents": "3.00",
            "averageRank": "1.83",
            "gamesPlayed": "6"
        },
        {
            "gamertag": "Dawn",
            "averageStars": "6.17",
            "averageOpponents": "3.50",
            "averageRank": "2.25",
            "gamesPlayed": "4"
        }
    ],
    "biggestStars": [
        {
            "gamertag": "C'tri",
            "averageStars": "1220.94",
            "averageOpponents": "4.40",
            "averageRank": "1.45",
            "gamesPlayed": "62"
        },
        {
            "gamertag": "Rayth",
            "averageStars": "973.02",
            "averageOpponents": "5.97",
            "averageRank": "2.05",
            "gamesPlayed": "39"
        },
        {
            "gamertag": "Achilles",
            "averageStars": "878.03",
            "averageOpponents": "4.77",
            "averageRank": "2.15",
            "gamesPlayed": "48"
        },
        {
            "gamertag": "Reboot",
            "averageStars": "391.62",
            "averageOpponents": "6.24",
            "averageRank": "3.48",
            "gamesPlayed": "25"
        },
        {
            "gamertag": "Robo_h34d",
            "averageStars": "356.94",
            "averageOpponents": "7.65",
            "averageRank": "4.57",
            "gamesPlayed": "23"
        },
        {
            "gamertag": "Goku",
            "averageStars": "335.16",
            "averageOpponents": "8.73",
            "averageRank": "3.82",
            "gamesPlayed": "11"
        },
        {
            "gamertag": "Jj",
            "averageStars": "320.23",
            "averageOpponents": "4.39",
            "averageRank": "2.48",
            "gamesPlayed": "31"
        },
        {
            "gamertag": "Mike Hunt",
            "averageStars": "276.20",
            "averageOpponents": "5.71",
            "averageRank": "3.54",
            "gamesPlayed": "24"
        },
        {
            "gamertag": "T D",
            "averageStars": "239.27",
            "averageOpponents": "8.38",
            "averageRank": "5.00",
            "gamesPlayed": "13"
        },
        {
            "gamertag": "Oscar",
            "averageStars": "162.83",
            "averageOpponents": "4.27",
            "averageRank": "1.87",
            "gamesPlayed": "15"
        },
        {
            "gamertag": "Minnie",
            "averageStars": "161.74",
            "averageOpponents": "8.70",
            "averageRank": "5.40",
            "gamesPlayed": "10"
        },
        {
            "gamertag": "JammyDodger",
            "averageStars": "154.49",
            "averageOpponents": "5.18",
            "averageRank": "2.27",
            "gamesPlayed": "11"
        },
        {
            "gamertag": "Billybob",
            "averageStars": "154.01",
            "averageOpponents": "6.60",
            "averageRank": "5.75",
            "gamesPlayed": "20"
        },
        {
            "gamertag": "Mindi",
            "averageStars": "143.35",
            "averageOpponents": "6.85",
            "averageRank": "4.92",
            "gamesPlayed": "13"
        },
        {
            "gamertag": "Winter",
            "averageStars": "142.93",
            "averageOpponents": "7.86",
            "averageRank": "5.71",
            "gamesPlayed": "7"
        },
        {
            "gamertag": "Shade",
            "averageStars": "127.45",
            "averageOpponents": "6.06",
            "averageRank": "5.00",
            "gamesPlayed": "16"
        },
        {
            "gamertag": "Angel of Death",
            "averageStars": "112.00",
            "averageOpponents": "2.87",
            "averageRank": "1.27",
            "gamesPlayed": "15"
        },
        {
            "gamertag": "Overdrive",
            "averageStars": "109.50",
            "averageOpponents": "3.23",
            "averageRank": "1.62",
            "gamesPlayed": "13"
        },
        {
            "gamertag": "404 Unf",
            "averageStars": "97.00",
            "averageOpponents": "3.00",
            "averageRank": "1.67",
            "gamesPlayed": "15"
        },
        {
            "gamertag": "Alpha",
            "averageStars": "91.78",
            "averageOpponents": "6.33",
            "averageRank": "5.50",
            "gamesPlayed": "12"
        },
        {
            "gamertag": "ThatGuysFriend",
            "averageStars": "89.78",
            "averageOpponents": "5.25",
            "averageRank": "2.63",
            "gamesPlayed": "8"
        },
        {
            "gamertag": "Damo",
            "averageStars": "80.89",
            "averageOpponents": "11.40",
            "averageRank": "9.00",
            "gamesPlayed": "5"
        },
        {
            "gamertag": "Dantboytank",
            "averageStars": "77.00",
            "averageOpponents": "1.95",
            "averageRank": "1.00",
            "gamesPlayed": "20"
        },
        {
            "gamertag": "Captain Kitty",
            "averageStars": "67.25",
            "averageOpponents": "4.33",
            "averageRank": "2.33",
            "gamesPlayed": "6"
        },
        {
            "gamertag": "<*(((<",
            "averageStars": "66.83",
            "averageOpponents": "4.33",
            "averageRank": "2.50",
            "gamesPlayed": "6"
        },
        {
            "gamertag": "Baby Yoda",
            "averageStars": "62.50",
            "averageOpponents": "2.87",
            "averageRank": "2.27",
            "gamesPlayed": "15"
        },
        {
            "gamertag": "Omega",
            "averageStars": "62.48",
            "averageOpponents": "8.00",
            "averageRank": "5.25",
            "gamesPlayed": "4"
        },
        {
            "gamertag": "Outlander",
            "averageStars": "60.00",
            "averageOpponents": "3.22",
            "averageRank": "2.00",
            "gamesPlayed": "9"
        },
        {
            "gamertag": "Korg",
            "averageStars": "60.00",
            "averageOpponents": "12.00",
            "averageRank": "10.00",
            "gamesPlayed": "4"
        },
        {
            "gamertag": "Andrew",
            "averageStars": "59.33",
            "averageOpponents": "3.50",
            "averageRank": "2.13",
            "gamesPlayed": "8"
        },
        {
            "gamertag": "Bfl2",
            "averageStars": "58.00",
            "averageOpponents": "3.67",
            "averageRank": "1.50",
            "gamesPlayed": "6"
        },
        {
            "gamertag": "Bored Cyber",
            "averageStars": "56.66",
            "averageOpponents": "3.10",
            "averageRank": "2.00",
            "gamesPlayed": "10"
        },
        {
            "gamertag": "Alpha 52",
            "averageStars": "55.00",
            "averageOpponents": "2.10",
            "averageRank": "1.10",
            "gamesPlayed": "10"
        },
        {
            "gamertag": "Stephen",
            "averageStars": "53.99",
            "averageOpponents": "3.50",
            "averageRank": "2.13",
            "gamesPlayed": "8"
        },
        {
            "gamertag": "Brodie",
            "averageStars": "53.00",
            "averageOpponents": "3.08",
            "averageRank": "2.42",
            "gamesPlayed": "12"
        },
        {
            "gamertag": "PlagueDoctor",
            "averageStars": "52.65",
            "averageOpponents": "5.14",
            "averageRank": "3.57",
            "gamesPlayed": "7"
        },
        {
            "gamertag": "DragonNinjaIsla",
            "averageStars": "51.00",
            "averageOpponents": "2.86",
            "averageRank": "1.57",
            "gamesPlayed": "7"
        },
        {
            "gamertag": "Johnny",
            "averageStars": "50.00",
            "averageOpponents": "2.67",
            "averageRank": "1.00",
            "gamesPlayed": "6"
        },
        {
            "gamertag": "James",
            "averageStars": "50.00",
            "averageOpponents": "3.50",
            "averageRank": "2.63",
            "gamesPlayed": "8"
        },
        {
            "gamertag": "Fancy Pants",
            "averageStars": "47.38",
            "averageOpponents": "5.00",
            "averageRank": "4.14",
            "gamesPlayed": "7"
        },
        {
            "gamertag": "SpeedyDylan",
            "averageStars": "44.80",
            "averageOpponents": "8.00",
            "averageRank": "6.25",
            "gamesPlayed": "4"
        },
        {
            "gamertag": "Mcbeardy",
            "averageStars": "42.66",
            "averageOpponents": "4.33",
            "averageRank": "2.83",
            "gamesPlayed": "6"
        },
        {
            "gamertag": "Arran",
            "averageStars": "42.50",
            "averageOpponents": "2.08",
            "averageRank": "1.42",
            "gamesPlayed": "12"
        },
        {
            "gamertag": "Super Philip",
            "averageStars": "42.00",
            "averageOpponents": "1.83",
            "averageRank": "1.83",
            "gamesPlayed": "23"
        },
        {
            "gamertag": "Face",
            "averageStars": "42.00",
            "averageOpponents": "3.00",
            "averageRank": "1.50",
            "gamesPlayed": "6"
        },
        {
            "gamertag": "Bfl1",
            "averageStars": "41.00",
            "averageOpponents": "3.67",
            "averageRank": "2.50",
            "gamesPlayed": "6"
        },
        {
            "gamertag": "Jackie",
            "averageStars": "40.25",
            "averageOpponents": "2.30",
            "averageRank": "1.60",
            "gamesPlayed": "10"
        },
        {
            "gamertag": "Ghost 57",
            "averageStars": "40.00",
            "averageOpponents": "3.00",
            "averageRank": "1.00",
            "gamesPlayed": "4"
        },
        {
            "gamertag": "Tonymcl1002",
            "averageStars": "38.33",
            "averageOpponents": "3.33",
            "averageRank": "2.00",
            "gamesPlayed": "6"
        },
        {
            "gamertag": "Soul",
            "averageStars": "37.90",
            "averageOpponents": "9.00",
            "averageRank": "6.67",
            "gamesPlayed": "3"
        }
    ]
}