{
    "ScoreTitle": "Star Quality for all known players, between 2019-10 and 2019-11",
    "ScoreGreaterOrEqualDate": "2019-11",
    "ScoreLessDate": "2019-10",
    "Player": [
        {},
        {
            "Name": "-=Valroc=-",
            "StarQualityPerGame": "25.76",
            "TotalStarQuality": "437.92",
            "AverageOpponents": "7.59",
            "gamesPlayed": 17,
            "AverageRank": "2.24",
            "ChangeInRank": "\u21910.26",
            "ChangeInPlayers": "\u21910.24",
            "ChangeInSQPerGame": "\u21914.16"
        },
        {
            "Name": "Sn3aky",
            "StarQualityPerGame": "18.98",
            "TotalStarQuality": "113.88",
            "AverageOpponents": "7.33",
            "gamesPlayed": 6,
            "AverageRank": "2.83",
            "ChangeInRank": "\u21930.05",
            "ChangeInPlayers": "\u21930.67",
            "ChangeInSQPerGame": "\u21934.02"
        },
        {
            "Name": "Archer",
            "StarQualityPerGame": "18.19",
            "TotalStarQuality": "236.45",
            "AverageOpponents": "7.85",
            "gamesPlayed": 13,
            "AverageRank": "3.38",
            "ChangeInRank": "\u21911.33",
            "ChangeInPlayers": "\u21930.06",
            "ChangeInSQPerGame": "\u21914.93"
        },
        {
            "Name": "Entity",
            "StarQualityPerGame": "18.06",
            "TotalStarQuality": "108.38",
            "AverageOpponents": "8.50",
            "gamesPlayed": 6,
            "AverageRank": "4.00",
            "ChangeInRank": "\u21930.18",
            "ChangeInPlayers": "\u21911.18",
            "ChangeInSQPerGame": "\u21914.04"
        },
        {
            "Name": "<!-- Blaze -->",
            "StarQualityPerGame": "14.40",
            "TotalStarQuality": "288.01",
            "AverageOpponents": "7.15",
            "gamesPlayed": 20,
            "AverageRank": "3.55",
            "ChangeInRank": "\u21910.96",
            "ChangeInPlayers": "\u21930.45",
            "ChangeInSQPerGame": "\u21911.61"
        },
        {
            "Name": "Natsudragneel",
            "StarQualityPerGame": "13.09",
            "TotalStarQuality": "91.61",
            "AverageOpponents": "8.43",
            "gamesPlayed": 7,
            "AverageRank": "5.43",
            "ChangeInRank": "\u21930.11",
            "ChangeInPlayers": "\u21910.53",
            "ChangeInSQPerGame": "\u21911.36"
        },
        {
            "Name": "Assassin",
            "StarQualityPerGame": "12.93",
            "TotalStarQuality": "64.65",
            "AverageOpponents": "8.20",
            "gamesPlayed": 5,
            "AverageRank": "5.20",
            "ChangeInRank": "\u21934.20",
            "ChangeInPlayers": "\u21917.20",
            "ChangeInSQPerGame": "\u219111.93"
        },
        {
            "Name": "Unagi",
            "StarQualityPerGame": "12.87",
            "TotalStarQuality": "115.85",
            "AverageOpponents": "8.11",
            "gamesPlayed": 9,
            "AverageRank": "5.11",
            "ChangeInRank": "\u21930.96",
            "ChangeInPlayers": "\u21910.20",
            "ChangeInSQPerGame": "\u21932.20"
        },
        {
            "Name": "S N D",
            "StarQualityPerGame": "11.57",
            "TotalStarQuality": "81.00",
            "AverageOpponents": "6.43",
            "gamesPlayed": 7,
            "AverageRank": "3.57",
            "ChangeInRank": "\u21930.03",
            "ChangeInPlayers": "\u21931.28",
            "ChangeInSQPerGame": "\u21935.21"
        },
        {
            "Name": "(Apollo)",
            "StarQualityPerGame": "11.25",
            "TotalStarQuality": "45.00",
            "AverageOpponents": "3.75",
            "gamesPlayed": 4,
            "AverageRank": "1.25",
            "ChangeInRank": "\u21910.25",
            "ChangeInPlayers": "\u21911.75",
            "ChangeInSQPerGame": "\u21918.58"
        },
        {
            "Name": "Winter",
            "StarQualityPerGame": "11.11",
            "TotalStarQuality": "88.90",
            "AverageOpponents": "8.25",
            "gamesPlayed": 8,
            "AverageRank": "6.13",
            "ChangeInRank": "\u21910.44",
            "ChangeInPlayers": "\u21910.17",
            "ChangeInSQPerGame": "\u21911.16"
        },
        {
            "Name": "Custardio",
            "StarQualityPerGame": "10.59",
            "TotalStarQuality": "84.76",
            "AverageOpponents": "7.00",
            "gamesPlayed": 8,
            "AverageRank": "4.63",
            "ChangeInRank": null,
            "ChangeInPlayers": null,
            "ChangeInSQPerGame": null
        },
        {
            "Name": "HiJack",
            "StarQualityPerGame": "10.33",
            "TotalStarQuality": "196.33",
            "AverageOpponents": "7.26",
            "gamesPlayed": 19,
            "AverageRank": "5.11",
            "ChangeInRank": "\u21930.56",
            "ChangeInPlayers": "\u21930.03",
            "ChangeInSQPerGame": "\u21931.38"
        },
        {
            "Name": "[Insomniac]",
            "StarQualityPerGame": "10.16",
            "TotalStarQuality": "71.12",
            "AverageOpponents": "7.71",
            "gamesPlayed": 7,
            "AverageRank": "5.86",
            "ChangeInRank": "\u21930.40",
            "ChangeInPlayers": "\u21932.19",
            "ChangeInSQPerGame": "\u21937.84"
        },
        {
            "Name": "Killa",
            "StarQualityPerGame": "10.03",
            "TotalStarQuality": "80.26",
            "AverageOpponents": "6.63",
            "gamesPlayed": 8,
            "AverageRank": "4.38",
            "ChangeInRank": "\u21911.50",
            "ChangeInPlayers": "\u21933.75",
            "ChangeInSQPerGame": "\u21938.29"
        },
        {
            "Name": "Dazm",
            "StarQualityPerGame": "8.02",
            "TotalStarQuality": "24.05",
            "AverageOpponents": "7.67",
            "gamesPlayed": 3,
            "AverageRank": "7.33",
            "ChangeInRank": "\u21911.47",
            "ChangeInPlayers": "\u21931.53",
            "ChangeInSQPerGame": "\u21931.60"
        },
        {
            "Name": "Crashers",
            "StarQualityPerGame": "5.63",
            "TotalStarQuality": "22.50",
            "AverageOpponents": "3.75",
            "gamesPlayed": 4,
            "AverageRank": "2.50",
            "ChangeInRank": null,
            "ChangeInPlayers": null,
            "ChangeInSQPerGame": null
        },
        {
            "Name": "Mr ChatterBob",
            "StarQualityPerGame": "5.63",
            "TotalStarQuality": "22.50",
            "AverageOpponents": "3.75",
            "gamesPlayed": 4,
            "AverageRank": "2.50",
            "ChangeInRank": "\u21931.00",
            "ChangeInPlayers": "\u21911.75",
            "ChangeInSQPerGame": "\u21912.96"
        },
        {
            "Name": "Smasher",
            "StarQualityPerGame": "4.36",
            "TotalStarQuality": "13.09",
            "AverageOpponents": "4.00",
            "gamesPlayed": 3,
            "AverageRank": "3.67",
            "ChangeInRank": null,
            "ChangeInPlayers": null,
            "ChangeInSQPerGame": null
        },
        {
            "Name": "Pikachu100Clan",
            "StarQualityPerGame": "1.00",
            "TotalStarQuality": "1.00",
            "AverageOpponents": "1.00",
            "gamesPlayed": 1,
            "AverageRank": "1.00",
            "ChangeInRank": null,
            "ChangeInPlayers": null,
            "ChangeInSQPerGame": null
        },
        {
            "Name": "C'tri",
            "StarQualityPerGame": "1.00",
            "TotalStarQuality": "1.00",
            "AverageOpponents": "1.00",
            "gamesPlayed": 1,
            "AverageRank": "1.00",
            "ChangeInRank": null,
            "ChangeInPlayers": null,
            "ChangeInSQPerGame": null
        },
        {
            "Name": "Finley",
            "StarQualityPerGame": "1.00",
            "TotalStarQuality": "4.00",
            "AverageOpponents": "1.00",
            "gamesPlayed": 4,
            "AverageRank": "1.00",
            "ChangeInRank": null,
            "ChangeInPlayers": null,
            "ChangeInSQPerGame": null
        }
    ]
}